kaiserlift/__init__.py
kaiserlift/df_processers.py
kaiserlift/pipeline.py
kaiserlift/plot_utils.py
kaiserlift/running_pipeline.py
kaiserlift/running_processers.py
kaiserlift/running_viewers.py
kaiserlift/viewers.py
kaiserlift/webapp.py
kaiserlift-0.1.94.dist-info/licenses/LICENSE
kaiserlift-0.1.94.dist-info/METADATA
kaiserlift-0.1.94.dist-info/WHEEL
kaiserlift-0.1.94.dist-info/entry_points.txt
kaiserlift-0.1.94.dist-info/top_level.txt
kaiserlift-0.1.94.dist-info/RECORD
