Metadata-Version: 2.4
Name: kaiserlift
Version: 0.1.94
Summary: Science-based progressive overload system for weightlifting and running with Pareto optimization
Author-email: Douglas Kaiser <douglastkaiser@gmail.com>
License: MIT
Project-URL: Homepage, https://www.douglastkaiser.com/projects/#workoutPlanner
Project-URL: Documentation, https://github.com/douglastkaiser/kaiserlift#readme
Project-URL: Repository, https://github.com/douglastkaiser/kaiserlift
Project-URL: Bug Tracker, https://github.com/douglastkaiser/kaiserlift/issues
Keywords: fitness,weightlifting,progressive-overload,workout-optimization,running,pareto,1rm,strength-training,data-analysis
Classifier: Development Status :: 4 - Beta
Classifier: Intended Audience :: Developers
Classifier: Intended Audience :: End Users/Desktop
Classifier: Intended Audience :: Science/Research
Classifier: Topic :: Scientific/Engineering :: Visualization
Classifier: Topic :: Utilities
Classifier: License :: OSI Approved :: MIT License
Classifier: Programming Language :: Python :: 3
Classifier: Programming Language :: Python :: 3.8
Classifier: Programming Language :: Python :: 3.9
Classifier: Programming Language :: Python :: 3.10
Classifier: Programming Language :: Python :: 3.11
Classifier: Programming Language :: Python :: 3.12
Classifier: Programming Language :: Python :: 3.13
Classifier: Operating System :: OS Independent
Requires-Python: >=3.8
License-File: LICENSE
Requires-Dist: pandas
Requires-Dist: numpy
Requires-Dist: matplotlib
Requires-Dist: plotly
Requires-Dist: ipython
Provides-Extra: server
Requires-Dist: fastapi; extra == "server"
Requires-Dist: uvicorn; extra == "server"
Requires-Dist: python-multipart; extra == "server"
Requires-Dist: httpx; extra == "server"
Provides-Extra: dev
Requires-Dist: pytest>=7.0; extra == "dev"
Requires-Dist: pytest-cov>=4.0; extra == "dev"
Requires-Dist: pytest-benchmark>=4.0; extra == "dev"
Dynamic: license-file
